__init__.py
marc.py
marc-22.5.1.dist-info/LICENSE
marc-22.5.1.dist-info/METADATA
marc-22.5.1.dist-info/WHEEL
marc-22.5.1.dist-info/top_level.txt
marc-22.5.1.dist-info/RECORD
