Metadata-Version: 2.1
Name: marc
Version: 22.5.1
Summary: Markov chain generator
Home-page: https://github.com/maxhumber/marc
Author: Max Humber
Author-email: max.humber@gmail.com
License: MIT
Classifier: Development Status :: 5 - Production/Stable
Classifier: License :: OSI Approved :: MIT License
Classifier: Programming Language :: Python :: 3
Requires-Python: >=3.9
License-File: LICENSE
